NetkillerRadioFix1/README.md
NetkillerRadioFix1/__init__.py
NetkillerRadioFix1/__main__.py
NetkillerRadioFix1/file.epub
NetkillerRadioFix1/index.html
NetkillerRadioFix1/css/__init__.py
NetkillerRadioFix1/css/annotations.css
NetkillerRadioFix1/css/main.css
NetkillerRadioFix1/css/normalize.css
NetkillerRadioFix1/css/popup.css
NetkillerRadioFix1/font/__init__.py
NetkillerRadioFix1/font/fontello.eot
NetkillerRadioFix1/font/fontello.svg
NetkillerRadioFix1/font/fontello.ttf
NetkillerRadioFix1/font/fontello.woff
NetkillerRadioFix1/img/__init__.py
NetkillerRadioFix1/img/annotator-glyph-sprite.png
NetkillerRadioFix1/img/annotator-icon-sprite.png
NetkillerRadioFix1/img/apple-touch-icon.png
NetkillerRadioFix1/img/cancelfullscreen.png
NetkillerRadioFix1/img/close.png
NetkillerRadioFix1/img/fullscreen.png
NetkillerRadioFix1/img/loader.gif
NetkillerRadioFix1/img/menu-icon.png
NetkillerRadioFix1/img/save.png
NetkillerRadioFix1/img/saved.png
NetkillerRadioFix1/img/settings-s.png
NetkillerRadioFix1/img/settings.png
NetkillerRadioFix1/img/star.png
NetkillerRadioFix1/js/__init__.py
NetkillerRadioFix1/js/epub.js
NetkillerRadioFix1/js/epub.min.js
NetkillerRadioFix1/js/epub.min.map
NetkillerRadioFix1/js/hooks.min.js
NetkillerRadioFix1/js/hooks.min.map
NetkillerRadioFix1/js/reader.js
NetkillerRadioFix1/js/reader.js.map
NetkillerRadioFix1/js/reader.min.js
NetkillerRadioFix1/js/reader.min.map
NetkillerRadioFix1/js/hooks/__init__.py
NetkillerRadioFix1/js/hooks/extensions/__init__.py
NetkillerRadioFix1/js/hooks/extensions/highlight.js
NetkillerRadioFix1/js/libs/__init__.py
NetkillerRadioFix1/js/libs/jquery.min.js
NetkillerRadioFix1/js/libs/localforage.min.js
NetkillerRadioFix1/js/libs/screenfull.js
NetkillerRadioFix1/js/libs/screenfull.min.js
NetkillerRadioFix1/js/libs/zip.min.js
NetkillerRadioFix1/js/plugins/__init__.py
NetkillerRadioFix1/js/plugins/hypothesis.js
NetkillerRadioFix1/js/plugins/search.js
netkiller_radio_fix1-2025.3.24.1.dist-info/METADATA
netkiller_radio_fix1-2025.3.24.1.dist-info/WHEEL
netkiller_radio_fix1-2025.3.24.1.dist-info/entry_points.txt
netkiller_radio_fix1-2025.3.24.1.dist-info/top_level.txt
netkiller_radio_fix1-2025.3.24.1.dist-info/RECORD
